spic/__about__.py
spic/__init__.py
spic/app.py
spic/defaults.py
spic/emit.py
spic/encoders.py
spic/enums.py
spic/exception_handlers.py
spic/exceptions.py
spic/func_handler.py
spic/inspect.py
spic/middleware.py
spic/py.typed
spic/request.py
spic/responses.py
spic/routing.py
spic/types.py
spic/utils.py
spic/openapi/__init__.py
spic/openapi/models.py
spic/openapi/utils.py
spic/params/__init__.py
spic/params/params.py
spic-0.1.0.dist-info/METADATA
spic-0.1.0.dist-info/WHEEL
spic-0.1.0.dist-info/licenses/LICENSE.txt
spic-0.1.0.dist-info/RECORD
