Metadata-Version: 2.1
Name: spic
Version: 0.1.0
Summary: a little opinionated framework for creating spic & span apis
Project-URL: Documentation, https://github.com/joshua-auchincloss/spic#readme
Project-URL: Issues, https://github.com/joshua-auchincloss/spic/issues
Project-URL: Source, https://github.com/joshua-auchincloss/spic
Author-email: joshua-auchincloss <joshua.auchincloss@proton.me>
License-Expression: MIT
License-File: LICENSE.txt
Classifier: Development Status :: 4 - Beta
Classifier: Intended Audience :: Information Technology
Classifier: Intended Audience :: System Administrators
Classifier: License :: OSI Approved :: MIT License
Classifier: Operating System :: OS Independent
Classifier: Programming Language :: Python
Classifier: Programming Language :: Python :: 3.9
Classifier: Programming Language :: Python :: 3.10
Classifier: Programming Language :: Python :: 3.11
Classifier: Topic :: Internet :: WWW/HTTP
Classifier: Topic :: Internet :: WWW/HTTP :: HTTP Servers
Classifier: Topic :: Software Development
Classifier: Topic :: Software Development :: Libraries
Classifier: Topic :: Software Development :: Libraries :: Application Frameworks
Classifier: Topic :: Software Development :: Libraries :: Python Modules
Classifier: Typing :: Typed
Requires-Python: >=3.9
Requires-Dist: beartype
Requires-Dist: hypercorn
Requires-Dist: pyserde[json]
Requires-Dist: rich
Requires-Dist: srsly
Provides-Extra: dev
Requires-Dist: black; extra == 'dev'
Requires-Dist: coverage; extra == 'dev'
Requires-Dist: git-changelog; extra == 'dev'
Requires-Dist: httpx; extra == 'dev'
Requires-Dist: isort; extra == 'dev'
Requires-Dist: pytest-asyncio; extra == 'dev'
Requires-Dist: pytest-cov; extra == 'dev'
Requires-Dist: ruff; extra == 'dev'
Requires-Dist: starlette; extra == 'dev'
Provides-Extra: experimental
Requires-Dist: pydantic; extra == 'experimental'
Provides-Extra: grpc-compat
Requires-Dist: grpcio; extra == 'grpc-compat'
Requires-Dist: protobuf; extra == 'grpc-compat'
Provides-Extra: msgpack
Requires-Dist: msgpack; extra == 'msgpack'
